AUTHORS
ChangeLog
LICENSE
README.md
setup.cfg
setup.py
tox.ini
simport/__init__.py
simport.egg-info/PKG-INFO
simport.egg-info/SOURCES.txt
simport.egg-info/dependency_links.txt
simport.egg-info/not-zip-safe
simport.egg-info/pbr.json
simport.egg-info/top_level.txt
tests/localmodule.py
tests/test_simport.py
tests/external/__init__.py
tests/external/externalmodule.py