Metadata-Version: 1.1
Name: simport
Version: 0.2.dev16
Summary: simple import with python path management
Home-page: https://github.com/stackforge/stacktach-simport
Author: Dark Secret Software Inc.
Author-email: admin@darksecretsoftware.com
License: Apache-2
Keywords: import
Platform: UNKNOWN
Classifier: Development Status :: 3 - Alpha
Classifier: Environment :: Console
Classifier: Intended Audience :: Developers
Classifier: Intended Audience :: Information Technology
Classifier: License :: OSI Approved :: Apache Software License
Classifier: Operating System :: OS Independent
Classifier: Programming Language :: Python
Classifier: Topic :: Software Development :: Libraries :: Python Modules
